{
  "n": 98,
  "n_parsed": 98,
  "safety_reasoning_rate": 0.9285714285714286,
  "first_position_norm_mean": 0.10682114992006532,
  "extent_sentence_count_mean": 16.244897959183675,
  "extent_fraction_mean": 0.35275704992483004,
  "first_section_hist": {
    "cot": 86,
    "output": 5
  },
  "span_category_hist": {
    "risk_acknowledgment": 479,
    "policy_boundary": 189,
    "refusal_reasoning": 389,
    "intent_assessment": 134,
    "safer_alternative": 392,
    "other_safety_reasoning": 9
  }
}